envyte/__init__.py
envyte/__main__.py
envyte/cli.py
envyte/core.py
envyte/utils.py
envyte-0.1.0.dist-info/licenses/LICENSE
envyte-0.1.0.dist-info/METADATA
envyte-0.1.0.dist-info/WHEEL
envyte-0.1.0.dist-info/entry_points.txt
envyte-0.1.0.dist-info/top_level.txt
envyte-0.1.0.dist-info/RECORD
