Metadata-Version: 2.4
Name: envyte
Version: 0.1.0
Summary: Auto-load .env files and run commands or read envs in Python.
Author: Contemelia
License-Expression: MIT
Classifier: Programming Language :: Python :: 3
Classifier: Operating System :: OS Independent
Requires-Python: >=3.8
License-File: LICENSE
Requires-Dist: python-dotenv>=1.0.0
Dynamic: license-file
